diamond_shovel/__init__.py
diamond_shovel/main.py
diamond_shovel/version.py
diamond_shovel/cli/__init__.py
diamond_shovel/cli/historian.py
diamond_shovel/config/__init__.py
diamond_shovel/config/global_config.py
diamond_shovel/function/__init__.py
diamond_shovel/function/binary_manager.py
diamond_shovel/function/scheduler.py
diamond_shovel/function/task.py
diamond_shovel/install/__init__.py
diamond_shovel/install/config_generation.py
diamond_shovel/install/install_util.py
diamond_shovel/plugins/__init__.py
diamond_shovel/plugins/events.py
diamond_shovel/plugins/injects.py
diamond_shovel/plugins/library.py
diamond_shovel/plugins/load.py
diamond_shovel/plugins/manage.py
diamond_shovel/privileged/__init__.py
diamond_shovel/privileged/privileged_main.py
diamond_shovel/slave/__init__.py
diamond_shovel/slave/server.py
diamond_shovel/slave/route/__init__.py
diamond_shovel/slave/route/management.py
diamond_shovel/slave/route/plugin.py
diamond_shovel/slave/route/task.py
diamond_shovel/tests/__init__.py
diamond_shovel/utils/__init__.py
diamond_shovel/utils/func/__init__.py
diamond_shovel/utils/func/async_helper.py
diamond_shovel/utils/func/json_util.py
diamond_shovel/utils/func/lazy.py
diamond_shovel/utils/func/result_tidy_up.py
diamond_shovel/utils/func/retry_decorator.py
diamond_shovel-0.3.dev12.dist-info/licenses/LICENSE.md
diamond_shovel-0.3.dev12.dist-info/METADATA
diamond_shovel-0.3.dev12.dist-info/WHEEL
diamond_shovel-0.3.dev12.dist-info/entry_points.txt
diamond_shovel-0.3.dev12.dist-info/top_level.txt
diamond_shovel-0.3.dev12.dist-info/RECORD
