Metadata-Version: 2.4
Name: diamond-shovel
Version: 0.3.dev12
Summary: A high-performance task-processing framework designed for cybersecurity
Author-email: shovel@hscsec.cn
Maintainer-email: shovel@hscsec.cn
License: # GNU LESSER GENERAL PUBLIC LICENSE
Project-URL: Homepage, https://www.hscsec.cn
Project-URL: Documentation, https://diamond-shovel.github.io/shovel-wiki/
Project-URL: Repository, https://github.com/diamond-shovel/diamond-shovel
Project-URL: Issues, https://github.com/diamond-shovel/diamond-shovel/issues
Keywords: cybersecurity,task processing,asynchronous,fastapi,python,framework
Classifier: Development Status :: 3 - Alpha
Classifier: Intended Audience :: Developers
Classifier: Intended Audience :: Information Technology
Classifier: Intended Audience :: System Administrators
Classifier: Programming Language :: Python :: 3
Classifier: Topic :: Security
Classifier: Topic :: Software Development :: Libraries
Classifier: Topic :: Software Development :: Libraries :: Application Frameworks
Classifier: Topic :: Software Development :: Libraries :: Python Modules
Classifier: Operating System :: OS Independent
Classifier: Framework :: FastAPI
Classifier: Framework :: AsyncIO
Requires-Python: >=3.10
License-File: LICENSE.md
Requires-Dist: annotated-types==0.7.0
Requires-Dist: anyio==4.9.0
Requires-Dist: click==8.2.1
Requires-Dist: colorlog==6.9.0
Requires-Dist: dill==0.4.0
Requires-Dist: fastapi==0.115.12
Requires-Dist: h11==0.14.0
Requires-Dist: idna==3.10
Requires-Dist: kink==0.8.1
Requires-Dist: pydantic==2.11.5
Requires-Dist: sniffio==1.3.1
Requires-Dist: typing-inspection==0.4.0
Requires-Dist: typing_extensions==4.14.0
Requires-Dist: uvicorn==0.34.0
Requires-Dist: websockets==15.0.1
Requires-Dist: python-multipart~=0.0.20
Requires-Dist: cryptography==45.0.4
Dynamic: license-file
